[
    {
        "user": "torvalds",
        "repo": "linux",
        "branch": "8a696a29c6905594e4abf78eaafcb62165ac61f1",
        "root": "scripts/kconfig",
        "file": [
            "lxdialog/checklist.c",
            "lxdialog/dialog.h",
            "lxdialog/inputbox.c",
            "lxdialog/menubox.c",
            "lxdialog/textbox.c",
            "lxdialog/util.c",
            "lxdialog/yesno.c",
            "confdata.c",
            "expr.c",
            "expr.h",
            "internal.h",
            "lexer.l",
            "list.h",
            "lkc_proto.h",
            "lkc.h",
            "mconf.c",
            "menu.c",
            "mnconf-common.h",
            "mnconf-common.c",
            "parser.y",
            "preprocess.c",
            "symbol.c",
            "util.c"
        ],
        "dir": []
    },
    {
        "user": "p-ranav",
        "repo": "argparse",
        "branch": "69dabd88a8e6680b1a1a18397eb3e165e4019ce6",
        "root": "include/argparse",
        "file": [
            "argparse.hpp"
        ],
        "dir": []
    }
]